{
  "swagger": "2.0",
  "info": {
    "version": "1.0.0",
    "title": "Meine API",
    "description": "Dokumentation meiner API"
  },
  "host": "localhost:3000",
  "basePath": "/",
  "tags": [
    {
      "name": "Books",
      "description": "Endpoints für Bücher"
    },
    {
      "name": "Lends",
      "description": "Endpoints für Ausleihen"
    }
  ],
  "schemes": [
    "http"
  ],
  "consumes": [
    "application/json"
  ],
  "produces": [
    "application/json"
  ],
  "paths": {
    "/books": {
      "get": {
        "description": "",
        "responses": {
          "200": {
            "description": "OK"
          }
        }
      },
      "post": {
        "description": "",
        "responses": {
          "200": {
            "description": "OK"
          }
        }
      }
    },
    "/books/{isbn}": {
      "get": {
        "description": "",
        "parameters": [
          {
            "name": "isbn",
            "in": "path",
            "required": true,
            "type": "string"
          }
        ],
        "responses": {
          "200": {
            "description": "OK"
          },
          "404": {
            "description": "Not Found"
          }
        }
      },
      "put": {
        "description": "",
        "parameters": [
          {
            "name": "isbn",
            "in": "path",
            "required": true,
            "type": "string"
          }
        ],
        "responses": {
          "200": {
            "description": "OK"
          },
          "404": {
            "description": "Not Found"
          }
        }
      },
      "delete": {
        "description": "",
        "parameters": [
          {
            "name": "isbn",
            "in": "path",
            "required": true,
            "type": "string"
          }
        ],
        "responses": {
          "200": {
            "description": "OK"
          },
          "404": {
            "description": "Not Found"
          }
        }
      },
      "patch": {
        "description": "",
        "parameters": [
          {
            "name": "isbn",
            "in": "path",
            "required": true,
            "type": "string"
          }
        ],
        "responses": {
          "200": {
            "description": "OK"
          },
          "404": {
            "description": "Not Found"
          }
        }
      }
    },
    "/lends": {
      "get": {
        "description": "",
        "responses": {
          "200": {
            "description": "OK"
          }
        }
      },
      "post": {
        "description": "",
        "parameters": [
          {
            "name": "isbn",
            "in": "query",
            "type": "string"
          }
        ],
        "responses": {
          "200": {
            "description": "OK"
          }
        }
      }
    },
    "/lends/{id}": {
      "get": {
        "description": "",
        "parameters": [
          {
            "name": "id",
            "in": "path",
            "required": true,
            "type": "string"
          }
        ],
        "responses": {
          "200": {
            "description": "OK"
          }
        }
      },
      "patch": {
        "description": "",
        "parameters": [
          {
            "name": "id",
            "in": "path",
            "required": true,
            "type": "string"
          },
          {
            "name": "isbn",
            "in": "query",
            "type": "string"
          }
        ],
        "responses": {
          "200": {
            "description": "OK"
          }
        }
      }
    }
  }
}